configs/__init__.py
configs/__main__.py
configs/cli.py
configs/config.py
configs/transform/__init__.py
configs/transform/env.py
configs/vault/__init__.py
configs/vault/aws.py
configs/vault/sops.py
configs/vault/stack.py
configs_adampippin-0.0.6.dist-info/DESCRIPTION.rst
configs_adampippin-0.0.6.dist-info/METADATA
configs_adampippin-0.0.6.dist-info/RECORD
configs_adampippin-0.0.6.dist-info/WHEEL
configs_adampippin-0.0.6.dist-info/entry_points.txt
configs_adampippin-0.0.6.dist-info/metadata.json
configs_adampippin-0.0.6.dist-info/top_level.txt
